<annotation>
	<folder>Images</folder>
	<filename>1657444774395.png</filename>
	<path>C:\Users\24484\Downloads\AI源码\目标检测\DNF_detetion\yolo基础1\data\Images\1657444774395.png</path>
	<source>
		<database>Unknown</database>
	</source>
	<size>
		<width>1280</width>
		<height>719</height>
		<depth>3</depth>
	</size>
	<segmented>0</segmented>
	<object>
		<name>gunner</name>
		<pose>Unspecified</pose>
		<truncated>0</truncated>
		<difficult>0</difficult>
		<bndbox>
			<xmin>439</xmin>
			<ymin>387</ymin>
			<xmax>591</xmax>
			<ymax>623</ymax>
		</bndbox>
	</object>
	<object>
		<name>monster</name>
		<pose>Unspecified</pose>
		<truncated>0</truncated>
		<difficult>0</difficult>
		<bndbox>
			<xmin>137</xmin>
			<ymin>459</ymin>
			<xmax>367</xmax>
			<ymax>615</ymax>
		</bndbox>
	</object>
	<object>
		<name>monster</name>
		<pose>Unspecified</pose>
		<truncated>0</truncated>
		<difficult>0</difficult>
		<bndbox>
			<xmin>913</xmin>
			<ymin>450</ymin>
			<xmax>1034</xmax>
			<ymax>620</ymax>
		</bndbox>
	</object>
	<object>
		<name>monster</name>
		<pose>Unspecified</pose>
		<truncated>0</truncated>
		<difficult>0</difficult>
		<bndbox>
			<xmin>742</xmin>
			<ymin>377</ymin>
			<xmax>896</xmax>
			<ymax>570</ymax>
		</bndbox>
	</object>
</annotation>
